premeide_package_test2/__init__.py
premeide_package_test2/example.py
premeide_package_test2-0.0.4.dist-info/LICENSE
premeide_package_test2-0.0.4.dist-info/METADATA
premeide_package_test2-0.0.4.dist-info/WHEEL
premeide_package_test2-0.0.4.dist-info/top_level.txt
premeide_package_test2-0.0.4.dist-info/RECORD
