Metadata-Version: 2.1
Name: premeide-package-test2
Version: 0.0.4
Summary: DESCRIPTION 0.0.4
Author: premeide
Author-email: premeide@gmail.com
Keywords: python
Classifier: Development Status :: 1 - Planning
Classifier: Intended Audience :: Developers
Classifier: Programming Language :: Python :: 3
Classifier: Operating System :: Unix
Classifier: Operating System :: MacOS :: MacOS X
Classifier: Operating System :: Microsoft :: Windows
License-File: LICENSE
